pyyp/__init__.py
pyyp/api.py
pyyp/client.py
pyyp/compat.py
pyyp/exceptions.py
pyyp/models.py
pyyp/utils.py
pyyp-0.0.7.dist-info/DESCRIPTION.rst
pyyp-0.0.7.dist-info/METADATA
pyyp-0.0.7.dist-info/RECORD
pyyp-0.0.7.dist-info/WHEEL
pyyp-0.0.7.dist-info/metadata.json
pyyp-0.0.7.dist-info/top_level.txt
